torchlpc/__init__.py
torchlpc/core.py
torchlpc/parallel_scan.py
torchlpc/recurrence.py
torchlpc-0.6.dist-info/LICENSE
torchlpc-0.6.dist-info/METADATA
torchlpc-0.6.dist-info/WHEEL
torchlpc-0.6.dist-info/top_level.txt
torchlpc-0.6.dist-info/RECORD
