Metadata-Version: 2.1
Name: torchlpc
Version: 0.6
Summary: Fast, efficient, and differentiable time-varying LPC filtering in PyTorch.
Home-page: https://github.com/yoyololicon/torchlpc
Author: Chin-Yun Yu
Author-email: chin-yun.yu@qmul.ac.uk
Classifier: Programming Language :: Python :: 3
Classifier: License :: OSI Approved :: MIT License
Classifier: Operating System :: OS Independent
License-File: LICENSE
Requires-Dist: torch >=2.0
Requires-Dist: numpy
Requires-Dist: numba
